{
  "version": "6",
  "dialect": "sqlite",
  "id": "2f7fbda1-2f21-43f8-9113-d4ff7b054d83",
  "prevId": "86f694b8-ae90-4098-8f13-eff6ecdaa01f",
  "tables": {
    "blog_items": {
      "name": "blog_items",
      "columns": {
        "id": {
          "name": "id",
          "type": "integer",
          "primaryKey": true,
          "notNull": true,
          "autoincrement": true
        },
        "published_at": {
          "name": "published_at",
          "type": "integer",
          "primaryKey": false,
          "notNull": true,
          "autoincrement": false
        },
        "category": {
          "name": "category",
          "type": "text",
          "primaryKey": false,
          "notNull": true,
          "autoincrement": false,
          "default": "'Uncategorized'"
        },
        "title": {
          "name": "title",
          "type": "text",
          "primaryKey": false,
          "notNull": true,
          "autoincrement": false
        },
        "image_paths": {
          "name": "image_paths",
          "type": "text",
          "primaryKey": false,
          "notNull": false,
          "autoincrement": false
        },
        "sub_title": {
          "name": "sub_title",
          "type": "text",
          "primaryKey": false,
          "notNull": false,
          "autoincrement": false
        },
        "text": {
          "name": "text",
          "type": "text",
          "primaryKey": false,
          "notNull": true,
          "autoincrement": false
        },
        "priority": {
          "name": "priority",
          "type": "text",
          "primaryKey": false,
          "notNull": true,
          "autoincrement": false
        },
        "order_index": {
          "name": "order_index",
          "type": "integer",
          "primaryKey": false,
          "notNull": true,
          "autoincrement": false
        }
      },
      "indexes": {},
      "foreignKeys": {},
      "compositePrimaryKeys": {},
      "uniqueConstraints": {},
      "checkConstraints": {}
    }
  },
  "views": {},
  "enums": {},
  "_meta": {
    "schemas": {},
    "tables": {},
    "columns": {
      "\"blog_items\".\"img\"": "\"blog_items\".\"image_paths\""
    }
  },
  "internal": {
    "indexes": {}
  }
}